{
  "stats": {
    "batting": [
      {
        "rank": 1,
        "initial_name": "A Srivastav",
        "batsman_name": "Achal Srivastav",
        "batsman_id": "5246443",
        "runs": 560,
        "top_score": 111,
        "50s": 2,
        "100s": 1,
        "fours": 65,
        "sixes": 8,
        "balls": 513,
        "not_out": 3.0,
        "match_id": 15,
        "position": 3.466666666666667,
        "innings_to_count": 12.0,
        "average": 46.666666666666664
      },
      {
        "rank": 2,
        "initial_name": "V Venkat",
        "batsman_name": "Vaikkun Venkat",
        "batsman_id": "6035486",
        "runs": 394,
        "top_score": 94,
        "50s": 2,
        "100s": 0,
        "fours": 35,
        "sixes": 0,
        "balls": 438,
        "not_out": 4.0,
        "match_id": 10,
        "position": 1.8,
        "innings_to_count": 6.0,
        "average": 65.66666666666667
      },
      {
        "rank": 3,
        "initial_name": "A Menon",
        "batsman_name": "Abhishek Menon",
        "batsman_id": "6326962",
        "runs": 237,
        "top_score": 52,
        "50s": 1,
        "100s": 0,
        "fours": 30,
        "sixes": 1,
        "balls": 271,
        "not_out": 2.0,
        "match_id": 12,
        "position": 1.6666666666666667,
        "innings_to_count": 10.0,
        "average": 23.7
      },
      {
        "rank": 4,
        "initial_name": "D Sheth",
        "batsman_name": "Dilan Sheth",
        "batsman_id": "5086031",
        "runs": 224,
        "top_score": 61,
        "50s": 2,
        "100s": 0,
        "fours": 32,
        "sixes": 0,
        "balls": 204,
        "not_out": 3.0,
        "match_id": 11,
        "position": 4.363636363636363,
        "innings_to_count": 8.0,
        "average": 28.0
      },
      {
        "rank": 5,
        "initial_name": "R Anandkar",
        "batsman_name": "Rohil Anandkar",
        "batsman_id": "6853247",
        "runs": 120,
        "top_score": 77,
        "50s": 1,
        "100s": 0,
        "fours": 16,
        "sixes": 0,
        "balls": 143,
        "not_out": 1.0,
        "match_id": 3,
        "position": 2.3333333333333335,
        "innings_to_count": 2.0,
        "average": 60.0
      },
      {
        "rank": 6,
        "initial_name": "C Deane",
        "batsman_name": "Charles Deane",
        "batsman_id": "6035496",
        "runs": 112,
        "top_score": 34,
        "50s": 0,
        "100s": 0,
        "fours": 18,
        "sixes": 0,
        "balls": 91,
        "not_out": 3.0,
        "match_id": 8,
        "position": 6.5,
        "innings_to_count": 5.0,
        "average": 22.4
      },
      {
        "rank": 7,
        "initial_name": "J Grabinar",
        "batsman_name": "Joel Grabinar",
        "batsman_id": "6059722",
        "runs": 111,
        "top_score": 46,
        "50s": 0,
        "100s": 0,
        "fours": 12,
        "sixes": 4,
        "balls": 95,
        "not_out": 0.0,
        "match_id": 3,
        "position": 3.6666666666666665,
        "innings_to_count": 3.0,
        "average": 37.0
      },
      {
        "rank": 8,
        "initial_name": "A Konidena",
        "batsman_name": "Aadi Konidena",
        "batsman_id": "6662700",
        "runs": 90,
        "top_score": 52,
        "50s": 1,
        "100s": 0,
        "fours": 12,
        "sixes": 1,
        "balls": 117,
        "not_out": 2.0,
        "match_id": 9,
        "position": 2.6666666666666665,
        "innings_to_count": 7.0,
        "average": 12.857142857142858
      },
      {
        "rank": 9,
        "initial_name": "S Arun",
        "batsman_name": "Suhas Arun",
        "batsman_id": "6035494",
        "runs": 76,
        "top_score": 29,
        "50s": 0,
        "100s": 0,
        "fours": 9,
        "sixes": 0,
        "balls": 146,
        "not_out": 0.0,
        "match_id": 6,
        "position": 4.333333333333333,
        "innings_to_count": 6.0,
        "average": 12.666666666666666
      },
      {
        "rank": 10,
        "initial_name": "V Balaji",
        "batsman_name": "Vignesh Balaji",
        "batsman_id": "6753197",
        "runs": 67,
        "top_score": 40,
        "50s": 0,
        "100s": 0,
        "fours": 7,
        "sixes": 3,
        "balls": 59,
        "not_out": 0.0,
        "match_id": 4,
        "position": 4.0,
        "innings_to_count": 4.0,
        "average": 16.75
      },
      {
        "rank": 11,
        "initial_name": "R Shenoy",
        "batsman_name": "Rohan Shenoy",
        "batsman_id": "6429388",
        "runs": 49,
        "top_score": 49,
        "50s": 0,
        "100s": 0,
        "fours": 4,
        "sixes": 4,
        "balls": 35,
        "not_out": 0.0,
        "match_id": 1,
        "position": 7.0,
        "innings_to_count": 1.0,
        "average": 49.0
      },
      {
        "rank": 12,
        "initial_name": "V Thakrar",
        "batsman_name": "Vikram Thakrar",
        "batsman_id": "6818322",
        "runs": 45,
        "top_score": 25,
        "50s": 0,
        "100s": 0,
        "fours": 8,
        "sixes": 0,
        "balls": 36,
        "not_out": 1.0,
        "match_id": 3,
        "position": 5.0,
        "innings_to_count": 2.0,
        "average": 22.5
      },
      {
        "rank": 13,
        "initial_name": "D Bains",
        "batsman_name": "Dhiran Bains",
        "batsman_id": "7156500",
        "runs": 45,
        "top_score": 35,
        "50s": 0,
        "100s": 0,
        "fours": 6,
        "sixes": 0,
        "balls": 36,
        "not_out": 0.0,
        "match_id": 2,
        "position": 2.0,
        "innings_to_count": 2.0,
        "average": 22.5
      },
      {
        "rank": 14,
        "initial_name": "A Subramanian",
        "batsman_name": "Arjun Subramanian",
        "batsman_id": "7032759",
        "runs": 28,
        "top_score": 14,
        "50s": 0,
        "100s": 0,
        "fours": 1,
        "sixes": 0,
        "balls": 32,
        "not_out": 2.0,
        "match_id": 5,
        "position": 7.6,
        "innings_to_count": 3.0,
        "average": 9.333333333333334
      },
      {
        "rank": 15,
        "initial_name": "M Manley",
        "batsman_name": "Max Manley",
        "batsman_id": "6676522",
        "runs": 26,
        "top_score": 18,
        "50s": 0,
        "100s": 0,
        "fours": 2,
        "sixes": 0,
        "balls": 18,
        "not_out": 2.0,
        "match_id": 4,
        "position": 9.25,
        "innings_to_count": 2.0,
        "average": 13.0
      },
      {
        "rank": 16,
        "initial_name": "W Dunleavy",
        "batsman_name": "Will Dunleavy",
        "batsman_id": "7156507",
        "runs": 26,
        "top_score": 26,
        "50s": 0,
        "100s": 0,
        "fours": 3,
        "sixes": 0,
        "balls": 18,
        "not_out": 1.0,
        "match_id": 1,
        "position": 6.0,
        "innings_to_count": 0.0,
        "average": null
      },
      {
        "rank": 17,
        "initial_name": "S Sureshkumar",
        "batsman_name": "Sidhanth Sureshkumar",
        "batsman_id": "7007872",
        "runs": 24,
        "top_score": 19,
        "50s": 0,
        "100s": 0,
        "fours": 2,
        "sixes": 0,
        "balls": 35,
        "not_out": 0.0,
        "match_id": 2,
        "position": 4.5,
        "innings_to_count": 2.0,
        "average": 12.0
      },
      {
        "rank": 18,
        "initial_name": "S Kanakala",
        "batsman_name": "Sree Kanakala",
        "batsman_id": "7007869",
        "runs": 23,
        "top_score": 23,
        "50s": 0,
        "100s": 0,
        "fours": 1,
        "sixes": 1,
        "balls": 14,
        "not_out": 0.0,
        "match_id": 1,
        "position": 4.0,
        "innings_to_count": 1.0,
        "average": 23.0
      },
      {
        "rank": 19,
        "initial_name": "A Glover",
        "batsman_name": "Alex Glover",
        "batsman_id": "6035493",
        "runs": 20,
        "top_score": 11,
        "50s": 0,
        "100s": 0,
        "fours": 1,
        "sixes": 0,
        "balls": 22,
        "not_out": 2.0,
        "match_id": 3,
        "position": 7.666666666666667,
        "innings_to_count": 1.0,
        "average": 20.0
      },
      {
        "rank": 20,
        "initial_name": "C Dunleavy",
        "batsman_name": "Ciaran Dunleavy",
        "batsman_id": "6035487",
        "runs": 20,
        "top_score": 14,
        "50s": 0,
        "100s": 0,
        "fours": 1,
        "sixes": 0,
        "balls": 40,
        "not_out": 2.0,
        "match_id": 6,
        "position": 5.5,
        "innings_to_count": 4.0,
        "average": 5.0
      },
      {
        "rank": 21,
        "initial_name": "J Hryb",
        "batsman_name": "James Hryb",
        "batsman_id": "6057485",
        "runs": 18,
        "top_score": 8,
        "50s": 0,
        "100s": 0,
        "fours": 3,
        "sixes": 0,
        "balls": 17,
        "not_out": 2.0,
        "match_id": 4,
        "position": 9.5,
        "innings_to_count": 2.0,
        "average": 9.0
      },
      {
        "rank": 22,
        "initial_name": "R Shah",
        "batsman_name": "Rohan Shah",
        "batsman_id": "6984148",
        "runs": 13,
        "top_score": 8,
        "50s": 0,
        "100s": 0,
        "fours": 1,
        "sixes": 0,
        "balls": 31,
        "not_out": 0.0,
        "match_id": 2,
        "position": 3.5,
        "innings_to_count": 2.0,
        "average": 6.5
      },
      {
        "rank": 23,
        "initial_name": "M Gupta",
        "batsman_name": "Mridul Gupta",
        "batsman_id": "6181894",
        "runs": 9,
        "top_score": 9,
        "50s": 0,
        "100s": 0,
        "fours": 1,
        "sixes": 9,
        "balls": 9,
        "not_out": 0.0,
        "match_id": 1,
        "position": 4.0,
        "innings_to_count": 1.0,
        "average": 9.0
      },
      {
        "rank": 24,
        "initial_name": "I Mayor",
        "batsman_name": "Ishan Mayor",
        "batsman_id": "7156505",
        "runs": 6,
        "top_score": 6,
        "50s": 0,
        "100s": 0,
        "fours": 0,
        "sixes": 0,
        "balls": 9,
        "not_out": 0.0,
        "match_id": 1,
        "position": 6.0,
        "innings_to_count": 1.0,
        "average": 6.0
      },
      {
        "rank": 25,
        "initial_name": "H Whiteley",
        "batsman_name": "Hogan Whiteley",
        "batsman_id": "",
        "runs": 5,
        "top_score": 5,
        "50s": 0,
        "100s": 0,
        "fours": 1,
        "sixes": 0,
        "balls": 2,
        "not_out": 0.0,
        "match_id": 1,
        "position": 8.0,
        "innings_to_count": 1.0,
        "average": 5.0
      },
      {
        "rank": 26,
        "initial_name": "C Entwistle",
        "batsman_name": "Charlie Entwistle",
        "batsman_id": "7156512",
        "runs": 4,
        "top_score": 4,
        "50s": 0,
        "100s": 0,
        "fours": 0,
        "sixes": 0,
        "balls": 8,
        "not_out": 0.0,
        "match_id": 1,
        "position": 8.0,
        "innings_to_count": 1.0,
        "average": 4.0
      },
      {
        "rank": 27,
        "initial_name": "A Sufi",
        "batsman_name": "Ali Sufi",
        "batsman_id": "6445994",
        "runs": 4,
        "top_score": 3,
        "50s": 0,
        "100s": 0,
        "fours": 0,
        "sixes": 0,
        "balls": 18,
        "not_out": 0.0,
        "match_id": 3,
        "position": 8.666666666666666,
        "innings_to_count": 3.0,
        "average": 1.3333333333333333
      },
      {
        "rank": 28,
        "initial_name": "A Hussain",
        "batsman_name": "Adam Hussain",
        "batsman_id": "7084731",
        "runs": 2,
        "top_score": 2,
        "50s": 0,
        "100s": 0,
        "fours": 0,
        "sixes": 0,
        "balls": 11,
        "not_out": 0.0,
        "match_id": 1,
        "position": 7.0,
        "innings_to_count": 1.0,
        "average": 2.0
      },
      {
        "rank": 29,
        "initial_name": "R Patel",
        "batsman_name": "Rushil Patel",
        "batsman_id": "5440822",
        "runs": 1,
        "top_score": 1,
        "50s": 0,
        "100s": 0,
        "fours": 0,
        "sixes": 0,
        "balls": 3,
        "not_out": 0.0,
        "match_id": 1,
        "position": 7.0,
        "innings_to_count": 1.0,
        "average": 1.0
      },
      {
        "rank": 30,
        "initial_name": "A Riaz",
        "batsman_name": "Ahad Riaz",
        "batsman_id": "6057484",
        "runs": 1,
        "top_score": 1,
        "50s": 0,
        "100s": 0,
        "fours": 0,
        "sixes": 0,
        "balls": 4,
        "not_out": 0.0,
        "match_id": 1,
        "position": 7.0,
        "innings_to_count": 1.0,
        "average": 1.0
      },
      {
        "rank": 31,
        "initial_name": "C Miller",
        "batsman_name": "Charlie Miller",
        "batsman_id": "",
        "runs": 1,
        "top_score": 1,
        "50s": 0,
        "100s": 0,
        "fours": 0,
        "sixes": 0,
        "balls": 6,
        "not_out": 0.0,
        "match_id": 1,
        "position": 9.0,
        "innings_to_count": 1.0,
        "average": 1.0
      },
      {
        "rank": 32,
        "initial_name": "H Talati",
        "batsman_name": "Het Talati",
        "batsman_id": "7156508",
        "runs": 0,
        "top_score": 0,
        "50s": 0,
        "100s": 0,
        "fours": 0,
        "sixes": 0,
        "balls": 1,
        "not_out": 0.0,
        "match_id": 1,
        "position": 4.0,
        "innings_to_count": 1.0,
        "average": 0.0
      },
      {
        "rank": 33,
        "initial_name": "J Malton",
        "batsman_name": "James Malton",
        "batsman_id": "",
        "runs": 0,
        "top_score": 0,
        "50s": 0,
        "100s": 0,
        "fours": 0,
        "sixes": 0,
        "balls": 2,
        "not_out": 0.0,
        "match_id": 1,
        "position": 6.0,
        "innings_to_count": 1.0,
        "average": 0.0
      },
      {
        "rank": 34,
        "initial_name": "A Lobo",
        "batsman_name": "Ashish Lobo",
        "batsman_id": "6984147",
        "runs": 0,
        "top_score": 0,
        "50s": 0,
        "100s": 0,
        "fours": 0,
        "sixes": 0,
        "balls": 3,
        "not_out": 0.0,
        "match_id": 1,
        "position": 5.0,
        "innings_to_count": 1.0,
        "average": 0.0
      },
      {
        "rank": 35,
        "initial_name": "S Sankaranarayanan",
        "batsman_name": "Sanjay Sankaranarayanan",
        "batsman_id": "6779673",
        "runs": 0,
        "top_score": 0,
        "50s": 0,
        "100s": 0,
        "fours": 0,
        "sixes": 0,
        "balls": 3,
        "not_out": 1.0,
        "match_id": 2,
        "position": 9.5,
        "innings_to_count": 1.0,
        "average": 0.0
      },
      {
        "rank": 36,
        "initial_name": "L Williams",
        "batsman_name": "Lizzie Williams",
        "batsman_id": "5308275",
        "runs": 0,
        "top_score": 0,
        "50s": 0,
        "100s": 0,
        "fours": 0,
        "sixes": 0,
        "balls": 4,
        "not_out": 0.0,
        "match_id": 1,
        "position": 7.0,
        "innings_to_count": 1.0,
        "average": 0.0
      }
    ],
    "bowling": [
      {
        "rank": 1,
        "initial_name": "C Deane",
        "bowler_name": "Charles Deane",
        "bowler_id": "6035496",
        "wickets": 12,
        "max_wickets": 3,
        "5fers": 0,
        "balls": 323.0,
        "maidens": 3.0,
        "runs": 288.0,
        "match_id": 10,
        "overs": "53.5",
        "average": 24.0,
        "sr": 26.916666666666668,
        "econ": 5.34984520123839,
        "best_figures": "3/25"
      },
      {
        "rank": 2,
        "initial_name": "J Hryb",
        "bowler_name": "James Hryb",
        "bowler_id": "6057485",
        "wickets": 12,
        "max_wickets": 4,
        "5fers": 0,
        "balls": 274.0,
        "maidens": 0.0,
        "runs": 410.0,
        "match_id": 10,
        "overs": "45.4",
        "average": 34.166666666666664,
        "sr": 22.833333333333332,
        "econ": 8.978102189781023,
        "best_figures": "4/40"
      },
      {
        "rank": 3,
        "initial_name": "C Dunleavy",
        "bowler_name": "Ciaran Dunleavy",
        "bowler_id": "6035487",
        "wickets": 8,
        "max_wickets": 3,
        "5fers": 0,
        "balls": 138.0,
        "maidens": 3.0,
        "runs": 169.0,
        "match_id": 7,
        "overs": "23.0",
        "average": 21.125,
        "sr": 17.25,
        "econ": 7.347826086956522,
        "best_figures": "3/25"
      },
      {
        "rank": 4,
        "initial_name": "A Srivastav",
        "bowler_name": "Achal Srivastav",
        "bowler_id": "5246443",
        "wickets": 8,
        "max_wickets": 2,
        "5fers": 0,
        "balls": 257.0,
        "maidens": 0.0,
        "runs": 367.0,
        "match_id": 13,
        "overs": "42.5",
        "average": 45.875,
        "sr": 32.125,
        "econ": 8.568093385214008,
        "best_figures": "2/28"
      },
      {
        "rank": 5,
        "initial_name": "A Sufi",
        "bowler_name": "Ali Sufi",
        "bowler_id": "6445994",
        "wickets": 7,
        "max_wickets": 3,
        "5fers": 0,
        "balls": 228.0,
        "maidens": 6.0,
        "runs": 172.0,
        "match_id": 7,
        "overs": "38.0",
        "average": 24.571428571428573,
        "sr": 32.57142857142857,
        "econ": 4.526315789473684,
        "best_figures": "3/32"
      },
      {
        "rank": 6,
        "initial_name": "L Williams",
        "bowler_name": "Lizzie Williams",
        "bowler_id": "5308275",
        "wickets": 6,
        "max_wickets": 3,
        "5fers": 0,
        "balls": 132.0,
        "maidens": 4.0,
        "runs": 140.0,
        "match_id": 4,
        "overs": "22.0",
        "average": 23.333333333333332,
        "sr": 22.0,
        "econ": 6.363636363636363,
        "best_figures": "3/52"
      },
      {
        "rank": 7,
        "initial_name": "D Sheth",
        "bowler_name": "Dilan Sheth",
        "bowler_id": "5086031",
        "wickets": 6,
        "max_wickets": 3,
        "5fers": 0,
        "balls": 162.0,
        "maidens": 2.0,
        "runs": 153.0,
        "match_id": 5,
        "overs": "27.0",
        "average": 25.5,
        "sr": 27.0,
        "econ": 5.666666666666666,
        "best_figures": "3/21"
      },
      {
        "rank": 8,
        "initial_name": "A Glover",
        "bowler_name": "Alex Glover",
        "bowler_id": "6035493",
        "wickets": 5,
        "max_wickets": 1,
        "5fers": 0,
        "balls": 167.0,
        "maidens": 0.0,
        "runs": 217.0,
        "match_id": 7,
        "overs": "27.5",
        "average": 43.4,
        "sr": 33.4,
        "econ": 7.796407185628742,
        "best_figures": "1/18"
      },
      {
        "rank": 9,
        "initial_name": "S Sankaranarayanan",
        "bowler_name": "Sanjay Sankaranarayanan",
        "bowler_id": "6779673",
        "wickets": 4,
        "max_wickets": 2,
        "5fers": 0,
        "balls": 84.0,
        "maidens": 0.0,
        "runs": 93.0,
        "match_id": 3,
        "overs": "14.0",
        "average": 23.25,
        "sr": 21.0,
        "econ": 6.642857142857143,
        "best_figures": "2/26"
      },
      {
        "rank": 10,
        "initial_name": "M Manley",
        "bowler_name": "Max Manley",
        "bowler_id": "6676522",
        "wickets": 4,
        "max_wickets": 3,
        "5fers": 0,
        "balls": 168.0,
        "maidens": 1.0,
        "runs": 200.0,
        "match_id": 5,
        "overs": "28.0",
        "average": 50.0,
        "sr": 42.0,
        "econ": 7.142857142857142,
        "best_figures": "3/26"
      },
      {
        "rank": 11,
        "initial_name": "V Balaji",
        "bowler_name": "Vignesh Balaji",
        "bowler_id": "6753197",
        "wickets": 3,
        "max_wickets": 2,
        "5fers": 0,
        "balls": 36.0,
        "maidens": 1.0,
        "runs": 27.0,
        "match_id": 2,
        "overs": "6.0",
        "average": 9.0,
        "sr": 12.0,
        "econ": 4.5,
        "best_figures": "2/18"
      },
      {
        "rank": 12,
        "initial_name": "C Miller",
        "bowler_name": "Charlie Miller",
        "bowler_id": "",
        "wickets": 3,
        "max_wickets": 3,
        "5fers": 0,
        "balls": 36.0,
        "maidens": 0.0,
        "runs": 36.0,
        "match_id": 1,
        "overs": "6.0",
        "average": 12.0,
        "sr": 12.0,
        "econ": 6.0,
        "best_figures": "3/36"
      },
      {
        "rank": 13,
        "initial_name": "A Subramanian",
        "bowler_name": "Arjun Subramanian",
        "bowler_id": "7032759",
        "wickets": 3,
        "max_wickets": 2,
        "5fers": 0,
        "balls": 95.0,
        "maidens": 1.0,
        "runs": 78.0,
        "match_id": 3,
        "overs": "15.5",
        "average": 26.0,
        "sr": 31.666666666666668,
        "econ": 4.926315789473684,
        "best_figures": "2/15"
      },
      {
        "rank": 14,
        "initial_name": "H Whiteley",
        "bowler_name": "Hogan Whiteley",
        "bowler_id": "",
        "wickets": 2,
        "max_wickets": 2,
        "5fers": 0,
        "balls": 30.0,
        "maidens": 2.0,
        "runs": 9.0,
        "match_id": 1,
        "overs": "5.0",
        "average": 4.5,
        "sr": 15.0,
        "econ": 1.7999999999999998,
        "best_figures": "3/36"
      },
      {
        "rank": 15,
        "initial_name": "A Hussain",
        "bowler_name": "Adam Hussain",
        "bowler_id": "7084731",
        "wickets": 2,
        "max_wickets": 2,
        "5fers": 0,
        "balls": 48.0,
        "maidens": 1.0,
        "runs": 22.0,
        "match_id": 1,
        "overs": "8.0",
        "average": 11.0,
        "sr": 24.0,
        "econ": 2.75,
        "best_figures": "2/22"
      },
      {
        "rank": 16,
        "initial_name": "R Anandkar",
        "bowler_name": "Rohil Anandkar",
        "bowler_id": "6853247",
        "wickets": 2,
        "max_wickets": 2,
        "5fers": 0,
        "balls": 24.0,
        "maidens": 0.0,
        "runs": 45.0,
        "match_id": 1,
        "overs": "4.0",
        "average": 22.5,
        "sr": 12.0,
        "econ": 11.25,
        "best_figures": "2/45"
      },
      {
        "rank": 17,
        "initial_name": "S Kanakala",
        "bowler_name": "Sree Kanakala",
        "bowler_id": "7007869",
        "wickets": 2,
        "max_wickets": 2,
        "5fers": 0,
        "balls": 60.0,
        "maidens": 0.0,
        "runs": 53.0,
        "match_id": 2,
        "overs": "10.0",
        "average": 26.5,
        "sr": 30.0,
        "econ": 5.3,
        "best_figures": "2/33"
      },
      {
        "rank": 18,
        "initial_name": "W Dunleavy",
        "bowler_name": "Will Dunleavy",
        "bowler_id": "7156507",
        "wickets": 2,
        "max_wickets": 1,
        "5fers": 0,
        "balls": 47.0,
        "maidens": 0.0,
        "runs": 59.0,
        "match_id": 2,
        "overs": "7.5",
        "average": 29.5,
        "sr": 23.5,
        "econ": 7.531914893617021,
        "best_figures": "1/28"
      },
      {
        "rank": 19,
        "initial_name": "R Holm",
        "bowler_name": "Rory Holm",
        "bowler_id": "7032762",
        "wickets": 1,
        "max_wickets": 1,
        "5fers": 0,
        "balls": 30.0,
        "maidens": 0.0,
        "runs": 23.0,
        "match_id": 1,
        "overs": "5.0",
        "average": 23.0,
        "sr": 30.0,
        "econ": 4.6000000000000005,
        "best_figures": "1/23"
      },
      {
        "rank": 20,
        "initial_name": "R Shenoy",
        "bowler_name": "Rohan Shenoy",
        "bowler_id": "6429388",
        "wickets": 1,
        "max_wickets": 1,
        "5fers": 0,
        "balls": 52.0,
        "maidens": 0.0,
        "runs": 30.0,
        "match_id": 1,
        "overs": "8.4",
        "average": 30.0,
        "sr": 52.0,
        "econ": 3.4615384615384612,
        "best_figures": "1/30"
      },
      {
        "rank": 21,
        "initial_name": "R Shah",
        "bowler_name": "Rohan Shah",
        "bowler_id": "6984148",
        "wickets": 1,
        "max_wickets": 1,
        "5fers": 0,
        "balls": 24.0,
        "maidens": 0.0,
        "runs": 32.0,
        "match_id": 1,
        "overs": "4.0",
        "average": 32.0,
        "sr": 24.0,
        "econ": 8.0,
        "best_figures": "1/32"
      },
      {
        "rank": 22,
        "initial_name": "I Mayor",
        "bowler_name": "Ishan Mayor",
        "bowler_id": "7156505",
        "wickets": 1,
        "max_wickets": 1,
        "5fers": 0,
        "balls": 42.0,
        "maidens": 1.0,
        "runs": 38.0,
        "match_id": 1,
        "overs": "7.0",
        "average": 38.0,
        "sr": 42.0,
        "econ": 5.428571428571429,
        "best_figures": "1/38"
      },
      {
        "rank": 23,
        "initial_name": "J Grabinar",
        "bowler_name": "Joel Grabinar",
        "bowler_id": "6059722",
        "wickets": 1,
        "max_wickets": 1,
        "5fers": 0,
        "balls": 30.0,
        "maidens": 0.0,
        "runs": 49.0,
        "match_id": 2,
        "overs": "5.0",
        "average": 49.0,
        "sr": 30.0,
        "econ": 9.8,
        "best_figures": "1/37"
      },
      {
        "rank": 24,
        "initial_name": "V Venkat",
        "bowler_name": "Vaikkun Venkat",
        "bowler_id": "6035486",
        "wickets": 0,
        "max_wickets": 0,
        "5fers": 0,
        "balls": 18.0,
        "maidens": 0.0,
        "runs": 22.0,
        "match_id": 2,
        "overs": "3.0",
        "average": null,
        "sr": null,
        "econ": 7.333333333333334,
        "best_figures": "0/7"
      },
      {
        "rank": 25,
        "initial_name": "S Sureshkumar",
        "bowler_name": "Sidhanth Sureshkumar",
        "bowler_id": "7007872",
        "wickets": 0,
        "max_wickets": 0,
        "5fers": 0,
        "balls": 18.0,
        "maidens": 0.0,
        "runs": 31.0,
        "match_id": 1,
        "overs": "3.0",
        "average": null,
        "sr": null,
        "econ": 10.333333333333334,
        "best_figures": "0/31"
      },
      {
        "rank": 26,
        "initial_name": "A Menon",
        "bowler_name": "Abhishek Menon",
        "bowler_id": "6326962",
        "wickets": 0,
        "max_wickets": 0,
        "5fers": 0,
        "balls": 20.0,
        "maidens": 0.0,
        "runs": 35.0,
        "match_id": 2,
        "overs": "3.2",
        "average": null,
        "sr": null,
        "econ": 10.5,
        "best_figures": "0/15"
      },
      {
        "rank": 27,
        "initial_name": "A Riaz",
        "bowler_name": "Ahad Riaz",
        "bowler_id": "6057484",
        "wickets": 0,
        "max_wickets": 0,
        "5fers": 0,
        "balls": 42.0,
        "maidens": 0.0,
        "runs": 44.0,
        "match_id": 1,
        "overs": "7.0",
        "average": null,
        "sr": null,
        "econ": 6.2857142857142865,
        "best_figures": "0/44"
      }
    ],
    "fielding": [
      {
        "rank": 1,
        "fielder_name": "Unsure",
        "fielder_id": "",
        "dismissals": 19,
        "n_games": 7
      },
      {
        "rank": 2,
        "fielder_name": "Dilan Sheth",
        "fielder_id": "5086031",
        "dismissals": 7,
        "n_games": 5
      },
      {
        "rank": 3,
        "fielder_name": "Charles Deane",
        "fielder_id": "6035496",
        "dismissals": 5,
        "n_games": 3
      },
      {
        "rank": 4,
        "fielder_name": "Vikram Thakrar",
        "fielder_id": "6818322",
        "dismissals": 4,
        "n_games": 2
      },
      {
        "rank": 5,
        "fielder_name": "Vaikkun Venkat",
        "fielder_id": "6035486",
        "dismissals": 4,
        "n_games": 4
      },
      {
        "rank": 6,
        "fielder_name": "Rory Holm",
        "fielder_id": "7032762",
        "dismissals": 3,
        "n_games": 1
      },
      {
        "rank": 7,
        "fielder_name": "James Hryb",
        "fielder_id": "6057485",
        "dismissals": 3,
        "n_games": 2
      },
      {
        "rank": 8,
        "fielder_name": "Achal Srivastav",
        "fielder_id": "5246443",
        "dismissals": 2,
        "n_games": 1
      },
      {
        "rank": 9,
        "fielder_name": "Max Manley",
        "fielder_id": "6676522",
        "dismissals": 2,
        "n_games": 1
      },
      {
        "rank": 10,
        "fielder_name": "Abhishek Menon",
        "fielder_id": "6326962",
        "dismissals": 2,
        "n_games": 2
      },
      {
        "rank": 11,
        "fielder_name": "Ali Sufi",
        "fielder_id": "6445994",
        "dismissals": 2,
        "n_games": 2
      },
      {
        "rank": 12,
        "fielder_name": "Vignesh Balaji",
        "fielder_id": "6753197",
        "dismissals": 2,
        "n_games": 2
      },
      {
        "rank": 13,
        "fielder_name": "Ahad Riaz",
        "fielder_id": "6057484",
        "dismissals": 1,
        "n_games": 1
      },
      {
        "rank": 14,
        "fielder_name": "Dhiran Bains",
        "fielder_id": "7156500",
        "dismissals": 1,
        "n_games": 1
      },
      {
        "rank": 15,
        "fielder_name": "Het Talati",
        "fielder_id": "7156508",
        "dismissals": 1,
        "n_games": 1
      },
      {
        "rank": 16,
        "fielder_name": "Ishan Mayor",
        "fielder_id": "7156505",
        "dismissals": 1,
        "n_games": 1
      },
      {
        "rank": 17,
        "fielder_name": "Joel Grabinar",
        "fielder_id": "6059722",
        "dismissals": 1,
        "n_games": 1
      },
      {
        "rank": 18,
        "fielder_name": "Rohan Shah",
        "fielder_id": "6984148",
        "dismissals": 1,
        "n_games": 1
      },
      {
        "rank": 19,
        "fielder_name": "Rushil Patel",
        "fielder_id": "5440822",
        "dismissals": 1,
        "n_games": 1
      },
      {
        "rank": 20,
        "fielder_name": "Sanjay Sankaranarayanan",
        "fielder_id": "6779673",
        "dismissals": 1,
        "n_games": 1
      }
    ]
  },
  "season": 2026,
  "lastUpdated": "2026-07-24T08:37:36.581640"
}